pypraware-0.1.9.dist-info/DESCRIPTION.rst
pypraware-0.1.9.dist-info/METADATA
pypraware-0.1.9.dist-info/RECORD
pypraware-0.1.9.dist-info/WHEEL
pypraware-0.1.9.dist-info/metadata.json
pypraware-0.1.9.dist-info/top_level.txt
pypraware_crypto/__init__.py
pypraware_crypto/bcrypt.py
pypraware_crypto/bloom_filter.py
pypraware_crypto/bloomy.py
pypraware_crypto/choose_crypto.py
pypraware_crypto/helper.py
pypraware_crypto/hkdf.py
pypraware_crypto/interface.py
pypraware_crypto/pbkdf2.py
pypraware_crypto/pybloom.py
pypraware_crypto/sha.py
pypraware_crypto/utilspybloom.py
pypraware_normalize/__init__.py
pypraware_normalize/normalize.py
